cfnmacro/__init__.py
cfnmacro/cfnmacro.py
cfnmacro-0.1.0.dist-info/AUTHORS.rst
cfnmacro-0.1.0.dist-info/LICENSE
cfnmacro-0.1.0.dist-info/METADATA
cfnmacro-0.1.0.dist-info/WHEEL
cfnmacro-0.1.0.dist-info/top_level.txt
cfnmacro-0.1.0.dist-info/RECORD
