Metadata-Version: 2.1
Name: cfnmacro
Version: 0.1.0
Summary: Core/Common lib for all the cfnmacro modules
Home-page: https://github.com/johnpreston/cfnmacro
Author: John Mille
Author-email: john@lambda-my-aws.io
License: Apache Software License 2.0
Keywords: cfnmacro
Platform: UNKNOWN
Classifier: Development Status :: 2 - Pre-Alpha
Classifier: Intended Audience :: Developers
Classifier: License :: OSI Approved :: Apache Software License
Classifier: Natural Language :: English
Classifier: Programming Language :: Python :: 3
Classifier: Programming Language :: Python :: 3.6
Classifier: Programming Language :: Python :: 3.7
Requires-Dist: troposphere (>=2.4.7)
